odoo10_addon_auth_totp_password_security-10.0.1.0.0-py2.7-nspkg.pth
odoo/addons/auth_totp_password_security/README.rst
odoo/addons/auth_totp_password_security/__init__.py
odoo/addons/auth_totp_password_security/__manifest__.py
odoo/addons/auth_totp_password_security/controllers/__init__.py
odoo/addons/auth_totp_password_security/controllers/main.py
odoo/addons/auth_totp_password_security/tests/__init__.py
odoo/addons/auth_totp_password_security/tests/test_main.py
odoo10_addon_auth_totp_password_security-10.0.1.0.0.dist-info/DESCRIPTION.rst
odoo10_addon_auth_totp_password_security-10.0.1.0.0.dist-info/METADATA
odoo10_addon_auth_totp_password_security-10.0.1.0.0.dist-info/RECORD
odoo10_addon_auth_totp_password_security-10.0.1.0.0.dist-info/WHEEL
odoo10_addon_auth_totp_password_security-10.0.1.0.0.dist-info/metadata.json
odoo10_addon_auth_totp_password_security-10.0.1.0.0.dist-info/namespace_packages.txt
odoo10_addon_auth_totp_password_security-10.0.1.0.0.dist-info/top_level.txt
